ABToast/__init__.py
ABToast/abmain.py
ABToast/admin.py
ABToast/middleware.py
ABToast/models.py
ABToast/tests.py
ABToast/urls.py
ABToast/views.py
ABToast/utils/__init__.py
ABToast/utils/models.py
django_abtoast-1.2.0.dist-info/DESCRIPTION.rst
django_abtoast-1.2.0.dist-info/METADATA
django_abtoast-1.2.0.dist-info/RECORD
django_abtoast-1.2.0.dist-info/WHEEL
django_abtoast-1.2.0.dist-info/metadata.json
django_abtoast-1.2.0.dist-info/top_level.txt
