Metadata-Version: 2.0
Name: django-abtoast
Version: 1.2.0
Summary: ABToast is an A/B Testing app that is developed in django.
Home-page: https://github.com/htadg/ABToast
Author: Hiten Sharma
Author-email: sharmahiten3@gmail.com
License: MIT License
Platform: UNKNOWN
